setup.py
bdz_util/__init__.py
bdz_util.egg-info/PKG-INFO
bdz_util.egg-info/SOURCES.txt
bdz_util.egg-info/dependency_links.txt
bdz_util.egg-info/requires.txt
bdz_util.egg-info/top_level.txt
bdz_util/http_util/__init__.py
bdz_util/http_util/http_session.py
bdz_util/str_util/__init__.py