Metadata-Version: 1.0
Name: bdz-util
Version: 0.0.3
Summary: 常用工具类
Home-page: http://www.www.www.
Author: chenjian
Author-email: goudanbaba123@gmail.com
License: MIT Licence
Keywords: pip,util,bdz_util,httpclient
Platform: any
